lazy_streamfield/__init__.py
lazy_streamfield/datatypes.py
lazy_streamfield/py.typed
lazy_streamfield/streamblock.py
lazy_streamfield/streamfield.py
wagtail_lazy_streamfield-1.0.1.dist-info/METADATA
wagtail_lazy_streamfield-1.0.1.dist-info/WHEEL
wagtail_lazy_streamfield-1.0.1.dist-info/licenses/LICENSE
wagtail_lazy_streamfield-1.0.1.dist-info/RECORD
