Metadata-Version: 2.4
Name: wagtail-lazy-streamfield
Version: 1.0.1
Summary: Lazy-loading StreamField and StreamBlock for Wagtail that defers block instantiation to prevent circular imports and reduces migration bloat
Project-URL: Homepage, https://github.com/bartTC/wagtail-lazy-streamfield
Project-URL: Repository, https://github.com/bartTC/wagtail-lazy-streamfield.git
Project-URL: Issues, https://github.com/bartTC/wagtail-lazy-streamfield/issues
Author-email: Martin Mahner <martin@elephant.house>
License-Expression: MIT
License-File: LICENSE
Keywords: cms,django,streamfield,wagtail
Classifier: Development Status :: 4 - Beta
Classifier: Environment :: Web Environment
Classifier: Framework :: Django
Classifier: Framework :: Django :: 4.2
Classifier: Framework :: Django :: 5.0
Classifier: Framework :: Django :: 5.1
Classifier: Framework :: Django :: 5.2
Classifier: Framework :: Django :: 6.0
Classifier: Framework :: Wagtail
Classifier: Framework :: Wagtail :: 6
Classifier: Framework :: Wagtail :: 7
Classifier: Intended Audience :: Developers
Classifier: License :: OSI Approved :: MIT License
Classifier: Operating System :: OS Independent
Classifier: Programming Language :: Python
Classifier: Programming Language :: Python :: 3
Classifier: Programming Language :: Python :: 3.12
Classifier: Programming Language :: Python :: 3.13
Classifier: Programming Language :: Python :: 3.14
Classifier: Topic :: Internet :: WWW/HTTP :: Dynamic Content
Requires-Python: >=3.12
Requires-Dist: wagtail>=6.0
